osswiz/__init__.py
osswiz/_version.py
osswiz/py.typed
osswiz/util.py
osswiz/checks/__init__.py
osswiz/checks/fixtures.py
osswiz/checks/licenses.py
osswiz-0.1.0rc1.dist-info/METADATA
osswiz-0.1.0rc1.dist-info/WHEEL
osswiz-0.1.0rc1.dist-info/entry_points.txt
osswiz-0.1.0rc1.dist-info/licenses/LICENSE
osswiz-0.1.0rc1.dist-info/RECORD
