Metadata-Version: 2.3
Name: osswiz
Version: 0.1.0rc1
Summary: The Wizard of OSS - a tool to help you manage your open source projects
Author-email: Adrian Rumpold <a.rumpold@gmail.com>
License: Apache-2.0
License-File: LICENSE
Classifier: Development Status :: 3 - Alpha
Classifier: Intended Audience :: Developers
Classifier: License :: OSI Approved :: Apache Software License
Classifier: Programming Language :: Python :: 3
Classifier: Programming Language :: Python :: 3.10
Classifier: Programming Language :: Python :: 3.11
Classifier: Programming Language :: Python :: 3.12
Classifier: Programming Language :: Python :: 3.13
Requires-Python: >=3.10
Requires-Dist: repo-review[cli]>=0.11.2
